debounce.sv
module debounce (
    input clk, button,
    output reg button_edge
);
  localparam delay_val = 20; // 50us with clk period 20ns is ____ counts
  int count = 0;
  reg deb = 0;
  logic button_q0, button_pressed;
  
  // Your code here!
  always @(posedge clk) begin
    if (button != deb) begin
      deb <= button;
      count <= 0;
    end
    else if (count == delay_val) 
      button_pressed <= deb;
    else
      count <= count + 1;
  end 
  
  always_ff @(posedge clk) begin : edge_detect
      button_q0 <= button_pressed;
  end
  assign button_edge = (button_pressed > button_q0);

endmodule

debounce_tb.sv
`timescale 1ns/1ns
module debounce_tb;

    logic clk;
    logic button;/* verilator lint_off UNUSEDSIGNAL*/
    logic button_edge;
    logic button_pressed;

    debounce DUT (.*);

    initial forever #10 clk = ~clk; 
    
    initial begin
        $dumpfile("waveform.vcd");
        $dumpvars();
        clk = 0;
        button = 0;
        $display("Button is: %b, button_pressed is: %b correct button_pressed is 0", button, button_pressed);
        #100
        button = 1;
        #20000
        $display("Button is: %b, button_pressed is: %b, correct button_pressed is 0", button, button_pressed);
        button = 0;
        #2000
        $display("Button is: %b, button_pressed is: %b, correct button_pressed is 0", button, button_pressed);
        button = 1;
        #51000
        $display("Button is: %b, button_pressed is: %b, correct button_pressed is 1", button, button_pressed);
        #2000
        $finish();
    end

endmodule

waveforms/debounce_display.vcd
$version Generated by VerilatedVcd $end
$timescale 1ns $end

 $scope module TOP $end
  $scope module debounce_tb $end
   $var wire  1 ) button $end
   $var wire  1 # button_edge $end
   $var wire  1 $ button_pressed $end
   $var wire  1 ( clk $end
   $scope module DUT $end
    $var wire  1 ) button $end
    $var wire  1 # button_edge $end
    $var wire  1 $ button_pressed $end
    $var wire  1 ' button_q0 $end
    $var wire  1 ( clk $end
    $var wire 32 % count [31:0] $end
    $var wire  1 & deb $end
    $var wire 32 * delay_val [31:0] $end
   $upscope $end
  $upscope $end
 $upscope $end
$enddefinitions $end


#0
0#
0$
b00000000000000000000000000000000 %
0&
0'
0(
0)
b00000000000000000000100111000100 *
#10
b00000000000000000000000000000001 %
1(
#20
0(
#30
b00000000000000000000000000000010 %
1(
#40
0(
#50
b00000000000000000000000000000011 %
1(
#60
0(
#70
b00000000000000000000000000000100 %
1(
#80
0(
#90
b00000000000000000000000000000101 %
1(
#100
0(
1)
#110
b00000000000000000000000000000000 %
1&
1(
#120
0(
#130
b00000000000000000000000000000001 %
1(
#140
0(
#150
b00000000000000000000000000000010 %
1(
#160
0(
#170
b00000000000000000000000000000011 %
1(
#180
0(
#190
b00000000000000000000000000000100 %
1(
#200
0(
#210
b00000000000000000000000000000101 %
1(
#220
0(
#230
b00000000000000000000000000000110 %
1(
#240
0(
#250
b00000000000000000000000000000111 %
1(
#260
0(
#270
b00000000000000000000000000001000 %
1(
#280
0(
#290
b00000000000000000000000000001001 %
1(
#300
0(
#310
b00000000000000000000000000001010 %
1(
#320
0(
#330
b00000000000000000000000000001011 %
1(
#340
0(
#350
b00000000000000000000000000001100 %
1(
#360
0(
#370
b00000000000000000000000000001101 %
1(
#380
0(
#390
b00000000000000000000000000001110 %
1(
#400
0(
#410
b00000000000000000000000000001111 %
1(
#420
0(
#430
b00000000000000000000000000010000 %
1(
#440
0(
#450
b00000000000000000000000000010001 %
1(
#460
0(
#470
b00000000000000000000000000010010 %
1(
#480
0(
#490
b00000000000000000000000000010011 %
1(
#500
0(
#510
b00000000000000000000000000010100 %
1(
#520
0(
#530
b00000000000000000000000000010101 %
1(
#540
0(
#550
b00000000000000000000000000010110 %
1(
#560
0(
#570
b00000000000000000000000000010111 %
1(
#580
0(
#590
b00000000000000000000000000011000 %
1(
#600
0(
#610
b00000000000000000000000000011001 %
1(
#620
0(
#630
b00000000000000000000000000011010 %
1(
#640
0(
#650
b00000000000000000000000000011011 %
1(
#660
0(
#670
b00000000000000000000000000011100 %
1(
#680
0(
#690
b00000000000000000000000000011101 %
1(
#700
0(
#710
b00000000000000000000000000011110 %
1(
#720
0(
#730
b00000000000000000000000000011111 %
1(
#740
0(
#750
b00000000000000000000000000100000 %
1(
#760
0(
#770
b00000000000000000000000000100001 %
1(
#780
0(
#790
b00000000000000000000000000100010 %
1(
#800
0(
#810
b00000000000000000000000000100011 %
1(
#820
0(
#830
b00000000000000000000000000100100 %
1(
#840
0(
#850
b00000000000000000000000000100101 %
1(
#860
0(
#870
b00000000000000000000000000100110 %
1(
#880
0(
#890
b00000000000000000000000000100111 %
1(
#900
0(
#910
b00000000000000000000000000101000 %
1(
#920
0(
#930
b00000000000000000000000000101001 %
1(
#940
0(
#950
b00000000000000000000000000101010 %
1(
#960
0(
#970
b00000000000000000000000000101011 %
1(
#980
0(
#990
b00000000000000000000000000101100 %
1(
#1000
0(
#1010
b00000000000000000000000000101101 %
1(
#1020
0(
#1030
b00000000000000000000000000101110 %
1(
#1040
0(
#1050
b00000000000000000000000000101111 %
1(
#1060
0(
#1070
b00000000000000000000000000110000 %
1(
#1080
0(
#1090
b00000000000000000000000000110001 %
1(
#1100
0(
#1110
b00000000000000000000000000110010 %
1(
#1120
0(
#1130
b00000000000000000000000000110011 %
1(
#1140
0(
#1150
b00000000000000000000000000110100 %
1(
#1160
0(
#1170
b00000000000000000000000000110101 %
1(
#1180
0(
#1190
b00000000000000000000000000110110 %
1(
#1200
0(
#1210
b00000000000000000000000000110111 %
1(
#1220
0(
#1230
b00000000000000000000000000111000 %
1(
#1240
0(
#1250
b00000000000000000000000000111001 %
1(
#1260
0(
#1270
b00000000000000000000000000111010 %
1(
#1280
0(
#1290
b00000000000000000000000000111011 %
1(
#1300
0(
#1310
b00000000000000000000000000111100 %
1(
#1320
0(
#1330
b00000000000000000000000000111101 %
1(
#1340
0(
#1350
b00000000000000000000000000111110 %
1(
#1360
0(
#1370
b00000000000000000000000000111111 %
1(
#1380
0(
#1390
b00000000000000000000000001000000 %
1(
#1400
0(
#1410
b00000000000000000000000001000001 %
1(
#1420
0(
#1430
b00000000000000000000000001000010 %
1(
#1440
0(
#1450
b00000000000000000000000001000011 %
1(
#1460
0(
#1470
b00000000000000000000000001000100 %
1(
#1480
0(
#1490
b00000000000000000000000001000101 %
1(
#1500
0(
#1510
b00000000000000000000000001000110 %
1(
#1520
0(
#1530
b00000000000000000000000001000111 %
1(
#1540
0(
#1550
b00000000000000000000000001001000 %
1(
#1560
0(
#1570
b00000000000000000000000001001001 %
1(
#1580
0(
#1590
b00000000000000000000000001001010 %
1(
#1600
0(
#1610
b00000000000000000000000001001011 %
1(
#1620
0(
#1630
b00000000000000000000000001001100 %
1(
#1640
0(
#1650
b00000000000000000000000001001101 %
1(
#1660
0(
#1670
b00000000000000000000000001001110 %
1(
#1680
0(
#1690
b00000000000000000000000001001111 %
1(
#1700
0(
#1710
b00000000000000000000000001010000 %
1(
#1720
0(
#1730
b00000000000000000000000001010001 %
1(
#1740
0(
#1750
b00000000000000000000000001010010 %
1(
#1760
0(
#1770
b00000000000000000000000001010011 %
1(
#1780
0(
#1790
b00000000000000000000000001010100 %
1(
#1800
0(
#1810
b00000000000000000000000001010101 %
1(
#1820
0(
#1830
b00000000000000000000000001010110 %
1(
#1840
0(
#1850
b00000000000000000000000001010111 %
1(
#1860
0(
#1870
b00000000000000000000000001011000 %
1(
#1880
0(
#1890
b00000000000000000000000001011001 %
1(
#1900
0(
#1910
b00000000000000000000000001011010 %
1(
#1920
0(
#1930
b00000000000000000000000001011011 %
1(
#1940
0(
#1950
b00000000000000000000000001011100 %
1(
#1960
0(
#1970
b00000000000000000000000001011101 %
1(
#1980
0(
#1990
b00000000000000000000000001011110 %
1(
#2000
0(
#2010
b00000000000000000000000001011111 %
1(
#2020
0(
#2030
b00000000000000000000000001100000 %
1(
#2040
0(
#2050
b00000000000000000000000001100001 %
1(
#2060
0(
#2070
b00000000000000000000000001100010 %
1(
#2080
0(
#2090
b00000000000000000000000001100011 %
1(
#2100
0(
#2110
b00000000000000000000000001100100 %
1(
#2120
0(
#2130
b00000000000000000000000001100101 %
1(
#2140
0(
#2150
b00000000000000000000000001100110 %
1(
#2160
0(
#2170
b00000000000000000000000001100111 %
1(
#2180
0(
#2190
b00000000000000000000000001101000 %
1(
#2200
0(
#2210
b00000000000000000000000001101001 %
1(
#2220
0(
#2230
b00000000000000000000000001101010 %
1(
#2240
0(
#2250
b00000000000000000000000001101011 %
1(
#2260
0(
#2270
b00000000000000000000000001101100 %
1(
#2280
0(
#2290
b00000000000000000000000001101101 %
1(
#2300
0(
#2310
b00000000000000000000000001101110 %
1(
#2320
0(
#2330
b00000000000000000000000001101111 %
1(
#2340
0(
#2350
b00000000000000000000000001110000 %
1(
#2360
0(
#2370
b00000000000000000000000001110001 %
1(
#2380
0(
#2390
b00000000000000000000000001110010 %
1(
#2400
0(
#2410
b00000000000000000000000001110011 %
1(
#2420
0(
#2430
b00000000000000000000000001110100 %
1(
#2440
0(
#2450
b00000000000000000000000001110101 %
1(
#2460
0(
#2470
b00000000000000000000000001110110 %
1(
#2480
0(
#2490
b00000000000000000000000001110111 %
1(
#2500
0(
#2510
b00000000000000000000000001111000 %
1(
#2520
0(
#2530
b00000000000000000000000001111001 %
1(
#2540
0(
#2550
b00000000000000000000000001111010 %
1(
#2560
0(
#2570
b00000000000000000000000001111011 %
1(
#2580
0(
#2590
b00000000000000000000000001111100 %
1(
#2600
0(
#2610
b00000000000000000000000001111101 %
1(
#2620
0(
#2630
b00000000000000000000000001111110 %
1(
#2640
0(
#2650
b00000000000000000000000001111111 %
1(
#2660
0(
#2670
b00000000000000000000000010000000 %
1(
#2680
0(
#2690
b00000000000000000000000010000001 %
1(
#2700
0(
#2710
b00000000000000000000000010000010 %
1(
#2720
0(
#2730
b00000000000000000000000010000011 %
1(
#2740
0(
#2750
b00000000000000000000000010000100 %
1(
#2760
0(
#2770
b00000000000000000000000010000101 %
1(
#2780
0(
#2790
b00000000000000000000000010000110 %
1(
#2800
0(
#2810
b00000000000000000000000010000111 %
1(
#2820
0(
#2830
b00000000000000000000000010001000 %
1(
#2840
0(
#2850
b00000000000000000000000010001001 %
1(
#2860
0(
#2870
b00000000000000000000000010001010 %
1(
#2880
0(
#2890
b00000000000000000000000010001011 %
1(
#2900
0(
#2910
b00000000000000000000000010001100 %
1(
#2920
0(
#2930
b00000000000000000000000010001101 %
1(
#2940
0(
#2950
b00000000000000000000000010001110 %
1(
#2960
0(
#2970
b00000000000000000000000010001111 %
1(
#2980
0(
#2990
b00000000000000000000000010010000 %
1(
#3000
0(
#3010
b00000000000000000000000010010001 %
1(
#3020
0(
#3030
b00000000000000000000000010010010 %
1(
#3040
0(
#3050
b00000000000000000000000010010011 %
1(
#3060
0(
#3070
b00000000000000000000000010010100 %
1(
#3080
0(
#3090
b00000000000000000000000010010101 %
1(
#3100
0(
#3110
b00000000000000000000000010010110 %
1(
#3120
0(
#3130
b00000000000000000000000010010111 %
1(
#3140
0(
#3150
b00000000000000000000000010011000 %
1(
#3160
0(
#3170
b00000000000000000000000010011001 %
1(
#3180
0(
#3190
b00000000000000000000000010011010 %
1(
#3200
0(
#3210
b00000000000000000000000010011011 %
1(
#3220
0(
#3230
b00000000000000000000000010011100 %
1(
#3240
0(
#3250
b00000000000000000000000010011101 %
1(
#3260
0(
#3270
b00000000000000000000000010011110 %
1(
#3280
0(
#3290
b00000000000000000000000010011111 %
1(
#3300
0(
#3310
b00000000000000000000000010100000 %
1(
#3320
0(
#3330
b00000000000000000000000010100001 %
1(
#3340
0(
#3350
b00000000000000000000000010100010 %
1(
#3360
0(
#3370
b00000000000000000000000010100011 %
1(
#3380
0(
#3390
b00000000000000000000000010100100 %
1(
#3400
0(
#3410
b00000000000000000000000010100101 %
1(
#3420
0(
#3430
b00000000000000000000000010100110 %
1(
#3440
0(
#3450
b00000000000000000000000010100111 %
1(
#3460
0(
#3470
b00000000000000000000000010101000 %
1(
#3480
0(
#3490
b00000000000000000000000010101001 %
1(
#3500
0(
#3510
b00000000000000000000000010101010 %
1(
#3520
0(
#3530
b00000000000000000000000010101011 %
1(
#3540
0(
#3550
b00000000000000000000000010101100 %
1(
#3560
0(
#3570
b00000000000000000000000010101101 %
1(
#3580
0(
#3590
b00000000000000000000000010101110 %
1(
#3600
0(
#3610
b00000000000000000000000010101111 %
1(
#3620
0(
#3630
b00000000000000000000000010110000 %
1(
#3640
0(
#3650
b00000000000000000000000010110001 %
1(
#3660
0(
#3670
b00000000000000000000000010110010 %
1(
#3680
0(
#3690
b00000000000000000000000010110011 %
1(
#3700
0(
#3710
b00000000000000000000000010110100 %
1(
#3720
0(
#3730
b00000000000000000000000010110101 %
1(
#3740
0(
#3750
b00000000000000000000000010110110 %
1(
#3760
0(
#3770
b00000000000000000000000010110111 %
1(
#3780
0(
#3790
b00000000000000000000000010111000 %
1(
#3800
0(
#3810
b00000000000000000000000010111001 %
1(
#3820
0(
#3830
b00000000000000000000000010111010 %
1(
#3840
0(
#3850
b00000000000000000000000010111011 %
1(
#3860
0(
#3870
b00000000000000000000000010111100 %
1(
#3880
0(
#3890
b00000000000000000000000010111101 %
1(
#3900
0(
#3910
b00000000000000000000000010111110 %
1(
#3920
0(
#3930
b00000000000000000000000010111111 %
1(
#3940
0(
#3950
b00000000000000000000000011000000 %
1(
#3960
0(
#3970
b00000000000000000000000011000001 %
1(
#3980
0(
#3990
b00000000000000000000000011000010 %
1(
#4000
0(
#4010
b00000000000000000000000011000011 %
1(
#4020
0(
#4030
b00000000000000000000000011000100 %
1(
#4040
0(
#4050
b00000000000000000000000011000101 %
1(
#4060
0(
#4070
b00000000000000000000000011000110 %
1(
#4080
0(
#4090
b00000000000000000000000011000111 %
1(
#4100
0(
#4110
b00000000000000000000000011001000 %
1(
#4120
0(
#4130
b00000000000000000000000011001001 %
1(
#4140
0(
#4150
b00000000000000000000000011001010 %
1(
#4160
0(
#4170
b00000000000000000000000011001011 %
1(
#4180
0(
#4190
b00000000000000000000000011001100 %
1(
#4200
0(
#4210
b00000000000000000000000011001101 %
1(
#4220
0(
#4230
b00000000000000000000000011001110 %
1(
#4240
0(
#4250
b00000000000000000000000011001111 %
1(
#4260
0(
#4270
b00000000000000000000000011010000 %
1(
#4280
0(
#4290
b00000000000000000000000011010001 %
1(
#4300
0(
#4310
b00000000000000000000000011010010 %
1(
#4320
0(
#4330
b00000000000000000000000011010011 %
1(
#4340
0(
#4350
b00000000000000000000000011010100 %
1(
#4360
0(
#4370
b00000000000000000000000011010101 %
1(
#4380
0(
#4390
b00000000000000000000000011010110 %
1(
#4400
0(
#4410
b00000000000000000000000011010111 %
1(
#4420
0(
#4430
b00000000000000000000000011011000 %
1(
#4440
0(
#4450
b00000000000000000000000011011001 %
1(
#4460
0(
#4470
b00000000000000000000000011011010 %
1(
#4480
0(
#4490
b00000000000000000000000011011011 %
1(
#4500
0(
#4510
b00000000000000000000000011011100 %
1(
#4520
0(
#4530
b00000000000000000000000011011101 %
1(
#4540
0(
#4550
b00000000000000000000000011011110 %
1(
#4560
0(
#4570
b00000000000000000000000011011111 %
1(
#4580
0(
#4590
b00000000000000000000000011100000 %
1(
#4600
0(
#4610
b00000000000000000000000011100001 %
1(
#4620
0(
#4630
b00000000000000000000000011100010 %
1(
#4640
0(
#4650
b00000000000000000000000011100011 %
1(
#4660
0(
#4670
b00000000000000000000000011100100 %
1(
#4680
0(
#4690
b00000000000000000000000011100101 %
1(
#4700
0(
#4710
b00000000000000000000000011100110 %
1(
#4720
0(
#4730
b00000000000000000000000011100111 %
1(
#4740
0(
#4750
b00000000000000000000000011101000 %
1(
#4760
0(
#4770
b00000000000000000000000011101001 %
1(
#4780
0(
#4790
b00000000000000000000000011101010 %
1(
#4800
0(
#4810
b00000000000000000000000011101011 %
1(
#4820
0(
#4830
b00000000000000000000000011101100 %
1(
#4840
0(
#4850
b00000000000000000000000011101101 %
1(
#4860
0(
#4870
b00000000000000000000000011101110 %
1(
#4880
0(
#4890
b00000000000000000000000011101111 %
1(
#4900
0(
#4910
b00000000000000000000000011110000 %
1(
#4920
0(
#4930
b00000000000000000000000011110001 %
1(
#4940
0(
#4950
b00000000000000000000000011110010 %
1(
#4960
0(
#4970
b00000000000000000000000011110011 %
1(
#4980
0(
#4990
b00000000000000000000000011110100 %
1(
#5000
0(
#5010
b00000000000000000000000011110101 %
1(
#5020
0(
#5030
b00000000000000000000000011110110 %
1(
#5040
0(
#5050
b00000000000000000000000011110111 %
1(
#5060
0(
#5070
b00000000000000000000000011111000 %
1(
#5080
0(
#5090
b00000000000000000000000011111001 %
1(
#5100
0(
#5110
b00000000000000000000000011111010 %
1(
#5120
0(
#5130
b00000000000000000000000011111011 %
1(
#5140
0(
#5150
b00000000000000000000000011111100 %
1(
#5160
0(
#5170
b00000000000000000000000011111101 %
1(
#5180
0(
#5190
b00000000000000000000000011111110 %
1(
#5200
0(
#5210
b00000000000000000000000011111111 %
1(
#5220
0(
#5230
b00000000000000000000000100000000 %
1(
#5240
0(
#5250
b00000000000000000000000100000001 %
1(
#5260
0(
#5270
b00000000000000000000000100000010 %
1(
#5280
0(
#5290
b00000000000000000000000100000011 %
1(
#5300
0(
#5310
b00000000000000000000000100000100 %
1(
#5320
0(
#5330
b00000000000000000000000100000101 %
1(
#5340
0(
#5350
b00000000000000000000000100000110 %
1(
#5360
0(
#5370
b00000000000000000000000100000111 %
1(
#5380
0(
#5390
b00000000000000000000000100001000 %
1(
#5400
0(
#5410
b00000000000000000000000100001001 %
1(
#5420
0(
#5430
b00000000000000000000000100001010 %
1(
#5440
0(
#5450
b00000000000000000000000100001011 %
1(
#5460
0(
#5470
b00000000000000000000000100001100 %
1(
#5480
0(
#5490
b00000000000000000000000100001101 %
1(
#5500
0(
#5510
b00000000000000000000000100001110 %
1(
#5520
0(
#5530
b00000000000000000000000100001111 %
1(
#5540
0(
#5550
b00000000000000000000000100010000 %
1(
#5560
0(
#5570
b00000000000000000000000100010001 %
1(
#5580
0(
#5590
b00000000000000000000000100010010 %
1(
#5600
0(
#5610
b00000000000000000000000100010011 %
1(
#5620
0(
#5630
b00000000000000000000000100010100 %
1(
#5640
0(
#5650
b00000000000000000000000100010101 %
1(
#5660
0(
#5670
b00000000000000000000000100010110 %
1(
#5680
0(
#5690
b00000000000000000000000100010111 %
1(
#5700
0(
#5710
b00000000000000000000000100011000 %
1(
#5720
0(
#5730
b00000000000000000000000100011001 %
1(
#5740
0(
#5750
b00000000000000000000000100011010 %
1(
#5760
0(
#5770
b00000000000000000000000100011011 %
1(
#5780
0(
#5790
b00000000000000000000000100011100 %
1(
#5800
0(
#5810
b00000000000000000000000100011101 %
1(
#5820
0(
#5830
b00000000000000000000000100011110 %
1(
#5840
0(
#5850
b00000000000000000000000100011111 %
1(
#5860
0(
#5870
b00000000000000000000000100100000 %
1(
#5880
0(
#5890
b00000000000000000000000100100001 %
1(
#5900
0(
#5910
b00000000000000000000000100100010 %
1(
#5920
0(
#5930
b00000000000000000000000100100011 %
1(
#5940
0(
#5950
b00000000000000000000000100100100 %
1(
#5960
0(
#5970
b00000000000000000000000100100101 %
1(
#5980
0(
#5990
b00000000000000000000000100100110 %
1(
#6000
0(
#6010
b00000000000000000000000100100111 %
1(
#6020
0(
#6030
b00000000000000000000000100101000 %
1(
#6040
0(
#6050
b00000000000000000000000100101001 %
1(
#6060
0(
#6070
b00000000000000000000000100101010 %
1(
#6080
0(
#6090
b00000000000000000000000100101011 %
1(
#6100
0(
#6110
b00000000000000000000000100101100 %
1(
#6120
0(
#6130
b00000000000000000000000100101101 %
1(
#6140
0(
#6150
b00000000000000000000000100101110 %
1(
#6160
0(
#6170
b00000000000000000000000100101111 %
1(
#6180
0(
#6190
b00000000000000000000000100110000 %
1(
#6200
0(
#6210
b00000000000000000000000100110001 %
1(
#6220
0(
#6230
b00000000000000000000000100110010 %
1(
#6240
0(
#6250
b00000000000000000000000100110011 %
1(
#6260
0(
#6270
b00000000000000000000000100110100 %
1(
#6280
0(
#6290
b00000000000000000000000100110101 %
1(
#6300
0(
#6310
b00000000000000000000000100110110 %
1(
#6320
0(
#6330
b00000000000000000000000100110111 %
1(
#6340
0(
#6350
b00000000000000000000000100111000 %
1(
#6360
0(
#6370
b00000000000000000000000100111001 %
1(
#6380
0(
#6390
b00000000000000000000000100111010 %
1(
#6400
0(
#6410
b00000000000000000000000100111011 %
1(
#6420
0(
#6430
b00000000000000000000000100111100 %
1(
#6440
0(
#6450
b00000000000000000000000100111101 %
1(
#6460
0(
#6470
b00000000000000000000000100111110 %
1(
#6480
0(
#6490
b00000000000000000000000100111111 %
1(
#6500
0(
#6510
b00000000000000000000000101000000 %
1(
#6520
0(
#6530
b00000000000000000000000101000001 %
1(
#6540
0(
#6550
b00000000000000000000000101000010 %
1(
#6560
0(
#6570
b00000000000000000000000101000011 %
1(
#6580
0(
#6590
b00000000000000000000000101000100 %
1(
#6600
0(
#6610
b00000000000000000000000101000101 %
1(
#6620
0(
#6630
b00000000000000000000000101000110 %
1(
#6640
0(
#6650
b00000000000000000000000101000111 %
1(
#6660
0(
#6670
b00000000000000000000000101001000 %
1(
#6680
0(
#6690
b00000000000000000000000101001001 %
1(
#6700
0(
#6710
b00000000000000000000000101001010 %
1(
#6720
0(
#6730
b00000000000000000000000101001011 %
1(
#6740
0(
#6750
b00000000000000000000000101001100 %
1(
#6760
0(
#6770
b00000000000000000000000101001101 %
1(
#6780
0(
#6790
b00000000000000000000000101001110 %
1(
#6800
0(
#6810
b00000000000000000000000101001111 %
1(
#6820
0(
#6830
b00000000000000000000000101010000 %
1(
#6840
0(
#6850
b00000000000000000000000101010001 %
1(
#6860
0(
#6870
b00000000000000000000000101010010 %
1(
#6880
0(
#6890
b00000000000000000000000101010011 %
1(
#6900
0(
#6910
b00000000000000000000000101010100 %
1(
#6920
0(
#6930
b00000000000000000000000101010101 %
1(
#6940
0(
#6950
b00000000000000000000000101010110 %
1(
#6960
0(
#6970
b00000000000000000000000101010111 %
1(
#6980
0(
#6990
b00000000000000000000000101011000 %
1(
#7000
0(
#7010
b00000000000000000000000101011001 %
1(
#7020
0(
#7030
b00000000000000000000000101011010 %
1(
#7040
0(
#7050
b00000000000000000000000101011011 %
1(
#7060
0(
#7070
b00000000000000000000000101011100 %
1(
#7080
0(
#7090
b00000000000000000000000101011101 %
1(
#7100
0(
#7110
b00000000000000000000000101011110 %
1(
#7120
0(
#7130
b00000000000000000000000101011111 %
1(
#7140
0(
#7150
b00000000000000000000000101100000 %
1(
#7160
0(
#7170
b00000000000000000000000101100001 %
1(
#7180
0(
#7190
b00000000000000000000000101100010 %
1(
#7200
0(
#7210
b00000000000000000000000101100011 %
1(
#7220
0(
#7230
b00000000000000000000000101100100 %
1(
#7240
0(
#7250
b00000000000000000000000101100101 %
1(
#7260
0(
#7270
b00000000000000000000000101100110 %
1(
#7280
0(
#7290
b00000000000000000000000101100111 %
1(
#7300
0(
#7310
b00000000000000000000000101101000 %
1(
#7320
0(
#7330
b00000000000000000000000101101001 %
1(
#7340
0(
#7350
b00000000000000000000000101101010 %
1(
#7360
0(
#7370
b00000000000000000000000101101011 %
1(
#7380
0(
#7390
b00000000000000000000000101101100 %
1(
#7400
0(
#7410
b00000000000000000000000101101101 %
1(
#7420
0(
#7430
b00000000000000000000000101101110 %
1(
#7440
0(
#7450
b00000000000000000000000101101111 %
1(
#7460
0(
#7470
b00000000000000000000000101110000 %
1(
#7480
0(
#7490
b00000000000000000000000101110001 %
1(
#7500
0(
#7510
b00000000000000000000000101110010 %
1(
#7520
0(
#7530
b00000000000000000000000101110011 %
1(
#7540
0(
#7550
b00000000000000000000000101110100 %
1(
#7560
0(
#7570
b00000000000000000000000101110101 %
1(
#7580
0(
#7590
b00000000000000000000000101110110 %
1(
#7600
0(
#7610
b00000000000000000000000101110111 %
1(
#7620
0(
#7630
b00000000000000000000000101111000 %
1(
#7640
0(
#7650
b00000000000000000000000101111001 %
1(
#7660
0(
#7670
b00000000000000000000000101111010 %
1(
#7680
0(
#7690
b00000000000000000000000101111011 %
1(
#7700
0(
#7710
b00000000000000000000000101111100 %
1(
#7720
0(
#7730
b00000000000000000000000101111101 %
1(
#7740
0(
#7750
b00000000000000000000000101111110 %
1(
#7760
0(
#7770
b00000000000000000000000101111111 %
1(
#7780
0(
#7790
b00000000000000000000000110000000 %
1(
#7800
0(
#7810
b00000000000000000000000110000001 %
1(
#7820
0(
#7830
b00000000000000000000000110000010 %
1(
#7840
0(
#7850
b00000000000000000000000110000011 %
1(
#7860
0(
#7870
b00000000000000000000000110000100 %
1(
#7880
0(
#7890
b00000000000000000000000110000101 %
1(
#7900
0(
#7910
b00000000000000000000000110000110 %
1(
#7920
0(
#7930
b00000000000000000000000110000111 %
1(
#7940
0(
#7950
b00000000000000000000000110001000 %
1(
#7960
0(
#7970
b00000000000000000000000110001001 %
1(
#7980
0(
#7990
b00000000000000000000000110001010 %
1(
#8000
0(
#8010
b00000000000000000000000110001011 %
1(
#8020
0(
#8030
b00000000000000000000000110001100 %
1(
#8040
0(
#8050
b00000000000000000000000110001101 %
1(
#8060
0(
#8070
b00000000000000000000000110001110 %
1(
#8080
0(
#8090
b00000000000000000000000110001111 %
1(
#8100
0(
#8110
b00000000000000000000000110010000 %
1(
#8120
0(
#8130
b00000000000000000000000110010001 %
1(
#8140
0(
#8150
b00000000000000000000000110010010 %
1(
#8160
0(
#8170
b00000000000000000000000110010011 %
1(
#8180
0(
#8190
b00000000000000000000000110010100 %
1(
#8200
0(
#8210
b00000000000000000000000110010101 %
1(
#8220
0(
#8230
b00000000000000000000000110010110 %
1(
#8240
0(
#8250
b00000000000000000000000110010111 %
1(
#8260
0(
#8270
b00000000000000000000000110011000 %
1(
#8280
0(
#8290
b00000000000000000000000110011001 %
1(
#8300
0(
#8310
b00000000000000000000000110011010 %
1(
#8320
0(
#8330
b00000000000000000000000110011011 %
1(
#8340
0(
#8350
b00000000000000000000000110011100 %
1(
#8360
0(
#8370
b00000000000000000000000110011101 %
1(
#8380
0(
#8390
b00000000000000000000000110011110 %
1(
#8400
0(
#8410
b00000000000000000000000110011111 %
1(
#8420
0(
#8430
b00000000000000000000000110100000 %
1(
#8440
0(
#8450
b00000000000000000000000110100001 %
1(
#8460
0(
#8470
b00000000000000000000000110100010 %
1(
#8480
0(
#8490
b00000000000000000000000110100011 %
1(
#8500
0(
#8510
b00000000000000000000000110100100 %
1(
#8520
0(
#8530
b00000000000000000000000110100101 %
1(
#8540
0(
#8550
b00000000000000000000000110100110 %
1(
#8560
0(
#8570
b00000000000000000000000110100111 %
1(
#8580
0(
#8590
b00000000000000000000000110101000 %
1(
#8600
0(
#8610
b00000000000000000000000110101001 %
1(
#8620
0(
#8630
b00000000000000000000000110101010 %
1(
#8640
0(
#8650
b00000000000000000000000110101011 %
1(
#8660
0(
#8670
b00000000000000000000000110101100 %
1(
#8680
0(
#8690
b00000000000000000000000110101101 %
1(
#8700
0(
#8710
b00000000000000000000000110101110 %
1(
#8720
0(
#8730
b00000000000000000000000110101111 %
1(
#8740
0(
#8750
b00000000000000000000000110110000 %
1(
#8760
0(
#8770
b00000000000000000000000110110001 %
1(
#8780
0(
#8790
b00000000000000000000000110110010 %
1(
#8800
0(
#8810
b00000000000000000000000110110011 %
1(
#8820
0(
#8830
b00000000000000000000000110110100 %
1(
#8840
0(
#8850
b00000000000000000000000110110101 %
1(
#8860
0(
#8870
b00000000000000000000000110110110 %
1(
#8880
0(
#8890
b00000000000000000000000110110111 %
1(
#8900
0(
#8910
b00000000000000000000000110111000 %
1(
#8920
0(
#8930
b00000000000000000000000110111001 %
1(
#8940
0(
#8950
b00000000000000000000000110111010 %
1(
#8960
0(
#8970
b00000000000000000000000110111011 %
1(
#8980
0(
#8990
b00000000000000000000000110111100 %
1(
#9000
0(
#9010
b00000000000000000000000110111101 %
1(
#9020
0(
#9030
b00000000000000000000000110111110 %
1(
#9040
0(
#9050
b00000000000000000000000110111111 %
1(
#9060
0(
#9070
b00000000000000000000000111000000 %
1(
#9080
0(
#9090
b00000000000000000000000111000001 %
1(
#9100
0(
#9110
b00000000000000000000000111000010 %
1(
#9120
0(
#9130
b00000000000000000000000111000011 %
1(
#9140
0(
#9150
b00000000000000000000000111000100 %
1(
#9160
0(
#9170
b00000000000000000000000111000101 %
1(
#9180
0(
#9190
b00000000000000000000000111000110 %
1(
#9200
0(
#9210
b00000000000000000000000111000111 %
1(
#9220
0(
#9230
b00000000000000000000000111001000 %
1(
#9240
0(
#9250
b00000000000000000000000111001001 %
1(
#9260
0(
#9270
b00000000000000000000000111001010 %
1(
#9280
0(
#9290
b00000000000000000000000111001011 %
1(
#9300
0(
#9310
b00000000000000000000000111001100 %
1(
#9320
0(
#9330
b00000000000000000000000111001101 %
1(
#9340
0(
#9350
b00000000000000000000000111001110 %
1(
#9360
0(
#9370
b00000000000000000000000111001111 %
1(
#9380
0(
#9390
b00000000000000000000000111010000 %
1(
#9400
0(
#9410
b00000000000000000000000111010001 %
1(
#9420
0(
#9430
b00000000000000000000000111010010 %
1(
#9440
0(
#9450
b00000000000000000000000111010011 %
1(
#9460
0(
#9470
b00000000000000000000000111010100 %
1(
#9480
0(
#9490
b00000000000000000000000111010101 %
1(
#9500
0(
#9510
b00000000000000000000000111010110 %
1(
#9520
0(
#9530
b00000000000000000000000111010111 %
1(
#9540
0(
#9550
b00000000000000000000000111011000 %
1(
#9560
0(
#9570
b00000000000000000000000111011001 %
1(
#9580
0(
#9590
b00000000000000000000000111011010 %
1(
#9600
0(
#9610
b00000000000000000000000111011011 %
1(
#9620
0(
#9630
b00000000000000000000000111011100 %
1(
#9640
0(
#9650
b00000000000000000000000111011101 %
1(
#9660
0(
#9670
b00000000000000000000000111011110 %
1(
#9680
0(
#9690
b00000000000000000000000111011111 %
1(
#9700
0(
