direction_display.sv
module direction_display(
    input enable,
    input      [1:0]  direc,
    output logic [6:0]  HEX0, // right
    output logic [6:0]  HEX1, // left
    output logic [6:0]  HEX2, // forward
    output logic [6:0]  HEX3  // reverse backwards
);

    always_comb begin
        if (enable) begin
            HEX0 = (direc == 2'b11)? 7'b0101111: 7'b1111111;
            HEX1 = (direc == 2'b10)? 7'b1000111: 7'b1111111;
            HEX2 = (direc == 2'b00)? 7'b0001110: 7'b1111111;
            HEX3 = (direc == 2'b01)? 7'b0000011: 7'b1111111;
        end
        else begin
            HEX0 = 7'b1111111;
            HEX1 = 7'b1111111;
            HEX2 = 7'b1111111;
            HEX3 = 7'b1111111;
        end
    end
endmodule

torque_display.sv
module torque_display(
    input enable,
    input      [1:0]  instruction,
    input      [1:0]  torque,
    output logic [8:0]  left_LED, // LEDR[17:9]
    output logic [8:0]  right_LED // LEDR[8:0]
);

    //torque values
    logic [3:0] zero = 4'b0000;
    logic [3:0] quart = 4'b0010; 
    logic [3:0] half = 4'b1000; 
    logic [3:0] three_quart = 4'b1100;
    logic [3:0] full = 4'b1111;

    always_comb begin: torque_display
        if (~enable) begin
            left_LED = {zero, 1'b0, zero};
            right_LED = {zero, 1'b0, zero};
        end

        //no extension version
        /* else begin
            left_LED = (instruction == 2'b00)? {zero, 1'b0, full}:  
                        (instruction == 2'b01)? {full, 1'b0, zero}: 
                        (instruction == 2'b10)? {zero, 1'b0, three_quart}:
                        (instruction == 2'b11)? {zero, 1'b0, full} : {zero, 1'b0, zero};

            right_LED = (instruction == 2'b00)? {zero, 1'b0, full}:
                        (instruction == 2'b01)? {full, 1'b0, zero}:
                        (instruction == 2'b10)? {zero, 1'b0, full}:
                        (instruction == 2'b11)? {zero, 1'b0, three_quart} : {zero, 1'b0, zero};
        end */   
		  
		  //extension version
        else begin
				case (instruction)
              2'b00:begin //forward
                 left_LED = (torque == 2'b00)? {zero, 1'b0, zero}:  
                     (torque == 2'b01)? {zero, 1'b0, half}: 
                     (torque == 2'b10)? {zero, 1'b0, three_quart}:
                     (torque == 2'b11)? {zero, 1'b0, full} : {zero, 1'b0, zero};

                 right_LED = (torque == 2'b00)? {zero, 1'b0, zero}:  
                     (torque == 2'b01)? {zero, 1'b0, half}: 
                     (torque == 2'b10)? {zero, 1'b0, three_quart}:
                     (torque == 2'b11)? {zero, 1'b0, full} : {zero, 1'b0, zero};
             end
             2'b01:begin //reverse
                 left_LED = (torque == 2'b00)? {zero, 1'b0, zero}:  
                     (torque == 2'b01)? {half, 1'b0, zero}: 
                     (torque == 2'b10)? {three_quart, 1'b0, zero}:
                     (torque == 2'b11)? {full, 1'b0, zero} : {zero, 1'b0, zero};

                 right_LED = (torque == 2'b00)? {zero, 1'b0, zero}:  
                     (torque == 2'b01)? {half, 1'b0, zero}: 
                     (torque == 2'b10)? {three_quart, 1'b0, zero}:
                     (torque == 2'b11)? {full, 1'b0, zero} : {zero, 1'b0, zero};
             end
             2'b10:begin //left
                 left_LED = (torque == 2'b00)? {zero, 1'b0, zero}:  
                     (torque == 2'b01)? {zero, 1'b0, quart}: 
                     (torque == 2'b10)? {zero, 1'b0, half}:
                     (torque == 2'b11)? {zero, 1'b0, full} : {zero, 1'b0, zero};

                 right_LED = (torque == 2'b00)? {zero, 1'b0, zero}:  
                     (torque == 2'b01)? {zero, 1'b0, half}: 
                     (torque == 2'b10)? {zero, 1'b0, three_quart}:
                     (torque == 2'b11)? {zero, 1'b0, full} : {zero, 1'b0, zero};
             end
             2'b11:begin
                 left_LED = (torque == 2'b00)? {zero, 1'b0, zero}:  
                     (torque == 2'b01)? {zero, 1'b0, half}: 
                     (torque == 2'b10)? {zero, 1'b0, three_quart}:
                     (torque == 2'b11)? {zero, 1'b0, full} : {zero, 1'b0, zero};

                 right_LED = (torque == 2'b00)? {zero, 1'b0, zero}:  
                     (torque == 2'b01)? {zero, 1'b0, quart}: 
                     (torque == 2'b10)? {zero, 1'b0, half}:
                     (torque == 2'b11)? {zero, 1'b0, full} : {zero, 1'b0, zero};
             end
          endcase  
         end 

    end
endmodule

FIFO.sv
module fifo (
  input        clk,
  input        rst,
  input        we,
  input        re,
  input        del,
  input        [3:0] data_in,
  output reg   [3:0] data_out,
  output       empty,
  output       full
);
    //exact same thing as lab 2 FIFO
    //except 2 commented parts

    //changed the width to 256 (5-bit address)
    reg [3:0]       ram [255:0];

    localparam a_width = 8; // 1 wider than ram depth 
    reg [a_width:0] r_ptr, w_ptr;

    always @(posedge clk) begin
        if (rst) begin
            r_ptr <= 0;
            w_ptr <= 0; 
        end
        // added new rule to move back one pointer
        else if (del) w_ptr <= w_ptr -1;
        else begin
            if (we & ~full) begin
                ram[w_ptr[a_width-1:0]] <= data_in;
                w_ptr <= w_ptr + 1;
            end
            if (re & ~empty) begin
                data_out <= ram[r_ptr[a_width-1:0]];
                r_ptr <= r_ptr + 1;
            end
        end
    end

    assign empty = (r_ptr == w_ptr+1)? 1:0;
    assign full = r_ptr[a_width-1:0] != w_ptr[a_width-1:0]? 0: 
                    r_ptr[a_width] != w_ptr[a_width]? 1:0;

endmodule

debounce.sv
// module debounce (
//     input clk, button,
//     output reg button_pressed
// );
//   localparam delay_val = 2500; // 50us with clk period 20ns is ____ counts
//   int count = 0;
//   reg deb = 0;
  
//   // Your code here!
//   always @(posedge clk) begin
//     if (button != deb) begin
//       deb <= button;
//       count <= 0;
//     end
//     else if (count == delay_val) 
//       button_pressed <= deb;
//     else
//       count <= count + 1;
//   end 

// endmodule

module debounce (
    input clk, button,
    output reg button_pressed
);
  parameter delay_val = 2; 
  integer count = 0;
  reg new_button_pressed=0;
  always @(posedge clk) begin
      if (button != new_button_pressed) begin
        new_button_pressed <= button;
        count <= 0;
      end
      else if (count == delay_val) button_pressed <= new_button_pressed;
      else count <= count + 1;
  end
endmodule

countdown.sv
`timescale 1ns/1ns
//The above compiler directive explicitly specifies <time unit>/<time precision>


module countdown (
    input             clk, 
    input             enable, 
    output logic      timer
);
	 localparam delay_val = 50000000;

    logic [27:0]clk_cnt = 0;

    //set timer to 1 for 1 clk cycle every 2s
    always_ff @(posedge clk)begin
        if(!enable) begin
            clk_cnt <= 0;
            timer <= 0;
        end
        else begin
            if (clk_cnt == delay_val-1) begin
                timer <= 1;
                clk_cnt <= 0;
            end
            else begin
                clk_cnt <= clk_cnt + 1;
                timer <= 0;
            end
        end
        
    end

endmodule

FSM.sv
module FSM(
    input [3:0] KEY, //save, execute, reset, delete (respectively)
    input [3:0]SW, //basic instruction/direction SW[1:0], torque level SW[3:2]
    input CLOCK50, //Clk
    output [6:0] HEX3, HEX2, HEX1, HEX0, //7 seg display
    output [17:0] LEDR //Left torque & right torque
);

    logic save, execute, reset, delete;
    logic write_enable, read_enable, timer_enable;
    logic [3:0]instruction;
    logic empty, full;     
	logic timer; // used but never assigned 
    enum {idle, saving,
	 waiting, read, display} state = idle; 

    always_ff @(posedge CLOCK50) begin
        case (state)
            idle: state <= (save)? saving: idle;
            saving: state <= (reset)? idle: waiting;
            waiting: state <= (reset)? idle:
                                (save)? saving:
                                (execute | full)? read: waiting;
            read: state <= (reset)? idle: 
                            (timer)? display: read;
            display: state <= (empty | reset)? idle: read;
        endcase
    end
    
    assign write_enable = (state == saving)? 1:0;
    assign read_enable = (state == read)? 1:0;
    assign timer_enable = (state == read | state == display)? 1:0;
	 countdown u_clock (.clk(CLOCK50), 
				  .enable(timer_enable), 
				  .timer(timer));

    debounce u_debounce0 (
        .clk(CLOCK50), 
        .button(KEY[0]),
        .button_pressed(delete));
    debounce u_debounce1 (
        .clk(CLOCK50), 
        .button(KEY[1]),
        .button_pressed(reset));
    debounce u_debounce2 (
        .clk(CLOCK50), 
        .button(KEY[2]),
        .button_pressed(execute));
    debounce u_debounce3 (
        .clk(CLOCK50), 
        .button(KEY[3]),
        .button_pressed(save));

    fifo u_fifo (
        .clk(CLOCK50),
        .rst(reset),
        .we(write_enable),
        .re(read_enable),
        .del(delete),
        .data_in(SW[3:0]),
        .data_out(instruction),
        .empty(empty),
        .full(full));

    torque_display u_torque(
    .enable(timer_enable),
    .instruction(instruction[1:0]),
    .torque(instruction[3:2]),
    .left_LED(LEDR[17:9]),
    .right_LED(LEDR[8:0]));

    direction_display u_direction(
    .enable(timer_enable),
    .direc(instruction[1:0]),
    .HEX0(HEX0), // right
    .HEX1(HEX1), // left
    .HEX2(HEX2), // forward
    .HEX3(HEX3)  // reverse backwards
);
endmodule

FSM_tb.sv
module FSM_tb;
    // Step 1: Define test bench variables:
    logic [3:0] KEY; //save, execute, reset, delete (respectively)
    logic [3:0]SW; //basic instruction/direction SW[1:0], torque level SW[3:2]
    logic CLOCK50; //Clk

    logic [6:0]  HEX0; // right
    logic [6:0]  HEX1; // left
    logic [6:0]  HEX2; // forward
    logic [6:0]  HEX3;  // reverse backwards
    logic [17:0] LEDR; //Left torque & right torque

    // Step 2: Instantiate Device Under Test:
    FSM DUT (.*); // SystemVerilog feature: `.*` automatically connects ports of the instantiated module to variables in this module with the same port/variable name!! So useful :D.

    // Step 3: Toggle the clock variable every 10 time units to create a clock signal **with period = 20 time units**:
    // initial forever #10 clk = ~clk; // forever is an infinite loop!

    // Log every clock cycle:
    initial begin
        forever begin // strobe: print values at end of the current timestep
            $strobe("t: %d ps, LEDR: %b, HEX0: %b, HEX1: %b, HEX2: %b, HEX3: %b", $time, LEDR, HEX0, HEX1, HEX2, HEX3);
            #10;
        end
    end

    initial forever #1 CLOCK50 = ~CLOCK50;

    // Step 4: Initial block with initial inputs. To specify later inputs, use the delay operator `#`.
    initial begin
        $dumpfile("test_fsm.vcd");  // Tell the simulator to dump variables into the 'waveform.vcd' file during the simulation. Required to produce a waveform .vcd file.
        $dumpvars();
        CLOCK50 = 0;
        #40;

        SW = 4'b0000; // forward 0
        KEY[3] = 1; // pressed save
        #10;
        KEY[3] = 0;
        #40;

        SW = 4'b0100; // forward 1
        KEY[3] = 1; // pressed save
        #10;
        KEY[3] = 0;
        #40;

        SW = 4'b1000; // forward 2
        KEY[3] = 1; // pressed save
        #10;
        KEY[3] = 0;
        #40;

        SW = 4'b1100; // forward 2
        KEY[3] = 1; // pressed save
        #10;
        KEY[3] = 0;
        #40;

        SW = 4'b1010; // left 2
        KEY[3] = 1; // pressed save
        #10;
        KEY[3] = 0;
        #40;

        KEY[2] = 1; // pressed execute/read
        #10;
        KEY[2] = 0;
        #40;

        #1200;



        $finish(); // Important: must end simulation (or it will go on forever!)
    end

endmodule

waveforms/test_fsm.vcd
$version Generated by VerilatedVcd $end
$timescale 1ns $end

 $scope module TOP $end
  $scope module FSM_tb $end
   $var wire  1 I CLOCK50 $end
   $var wire  7 ) HEX0 [6:0] $end
   $var wire  7 * HEX1 [6:0] $end
   $var wire  7 + HEX2 [6:0] $end
   $var wire  7 , HEX3 [6:0] $end
   $var wire  4 # KEY [3:0] $end
   $var wire 18 - LEDR [17:0] $end
   $var wire  4 $ SW [3:0] $end
   $scope module DUT $end
    $var wire  1 I CLOCK50 $end
    $var wire  7 ) HEX0 [6:0] $end
    $var wire  7 * HEX1 [6:0] $end
    $var wire  7 + HEX2 [6:0] $end
    $var wire  7 , HEX3 [6:0] $end
    $var wire  4 # KEY [3:0] $end
    $var wire 18 - LEDR [17:0] $end
    $var wire  4 $ SW [3:0] $end
    $var wire  1 1 delete $end
    $var wire  1 6 empty $end
    $var wire  1 / execute $end
    $var wire  1 7 full $end
    $var wire  4 5 instruction [3:0] $end
    $var wire  1 3 read_enable $end
    $var wire  1 0 reset $end
    $var wire  1 . save $end
    $var wire 32 9 state [31:0] $end
    $var wire  1 8 timer $end
    $var wire  1 4 timer_enable $end
    $var wire  1 2 write_enable $end
    $scope module u_clock $end
     $var wire  1 I clk $end
     $var wire 28 : clk_cnt [27:0] $end
     $var wire  1 4 enable $end
     $var wire  1 8 timer $end
    $upscope $end
    $scope module u_debounce0 $end
     $var wire  1 % button $end
     $var wire  1 1 button_pressed $end
     $var wire  1 I clk $end
     $var wire 32 ; count [31:0] $end
     $var wire 32 J delay_val [31:0] $end
     $var wire  1 < new_button_pressed $end
    $upscope $end
    $scope module u_debounce1 $end
     $var wire  1 & button $end
     $var wire  1 0 button_pressed $end
     $var wire  1 I clk $end
     $var wire 32 = count [31:0] $end
     $var wire 32 J delay_val [31:0] $end
     $var wire  1 > new_button_pressed $end
    $upscope $end
    $scope module u_debounce2 $end
     $var wire  1 ' button $end
     $var wire  1 / button_pressed $end
     $var wire  1 I clk $end
     $var wire 32 ? count [31:0] $end
     $var wire 32 J delay_val [31:0] $end
     $var wire  1 @ new_button_pressed $end
    $upscope $end
    $scope module u_debounce3 $end
     $var wire  1 ( button $end
     $var wire  1 . button_pressed $end
     $var wire  1 I clk $end
     $var wire 32 A count [31:0] $end
     $var wire 32 J delay_val [31:0] $end
     $var wire  1 B new_button_pressed $end
    $upscope $end
    $scope module u_direction $end
     $var wire  7 ) HEX0 [6:0] $end
     $var wire  7 * HEX1 [6:0] $end
     $var wire  7 + HEX2 [6:0] $end
     $var wire  7 , HEX3 [6:0] $end
     $var wire  2 C direc [1:0] $end
     $var wire  1 4 enable $end
    $upscope $end
    $scope module u_fifo $end
     $var wire 32 K a_width [31:0] $end
     $var wire  1 I clk $end
     $var wire  4 $ data_in [3:0] $end
     $var wire  4 5 data_out [3:0] $end
     $var wire  1 1 del $end
     $var wire  1 6 empty $end
     $var wire  1 7 full $end
     $var wire  9 D r_ptr [8:0] $end
     $var wire  1 3 re $end
     $var wire  1 0 rst $end
     $var wire  9 E w_ptr [8:0] $end
     $var wire  1 2 we $end
    $upscope $end
    $scope module u_torque $end
     $var wire  1 4 enable $end
     $var wire  4 P full [3:0] $end
     $var wire  4 N half [3:0] $end
     $var wire  2 C instruction [1:0] $end
     $var wire  9 G left_LED [8:0] $end
     $var wire  4 M quart [3:0] $end
     $var wire  9 H right_LED [8:0] $end
     $var wire  4 O three_quart [3:0] $end
     $var wire  2 F torque [1:0] $end
     $var wire  4 L zero [3:0] $end
    $upscope $end
   $upscope $end
  $upscope $end
 $upscope $end
$enddefinitions $end


#0
b0000 #
b0000 $
0%
0&
0'
0(
b1111111 )
b1111111 *
b1111111 +
b1111111 ,
b000000000000000000 -
0.
0/
00
01
02
03
04
b0000 5
16
07
08
b00000000000000000000000000000000 9
b0000000000000000000000000000 :
b00000000000000000000000000000000 ;
0<
b00000000000000000000000000000000 =
0>
b00000000000000000000000000000000 ?
0@
b00000000000000000000000000000000 A
0B
b00 C
b000000000 D
b000000000 E
b00 F
b000000000 G
b000000000 H
0I
b00000000000000000000000000000010 J
b00000000000000000000000000001000 K
b0000 L
b0010 M
b1000 N
b1100 O
b1111 P
#1
b00000000000000000000000000000001 ;
b00000000000000000000000000000001 =
b00000000000000000000000000000001 ?
b00000000000000000000000000000001 A
1I
#2
0I
#3
b00000000000000000000000000000010 ;
b00000000000000000000000000000010 =
b00000000000000000000000000000010 ?
b00000000000000000000000000000010 A
1I
#4
0I
#5
1I
#6
0I
#7
1I
#8
0I
#9
1I
#10
0I
#11
1I
#12
0I
#13
1I
#14
0I
#15
1I
#16
0I
#17
1I
#18
0I
#19
1I
#20
0I
#21
1I
#22
0I
#23
1I
#24
0I
#25
1I
#26
0I
#27
1I
#28
0I
#29
1I
#30
0I
#31
1I
#32
0I
#33
1I
#34
0I
#35
1I
#36
0I
#37
1I
#38
0I
#39
1I
#40
b1000 #
1(
0I
#41
b00000000000000000000000000000000 A
1B
1I
#42
0I
#43
b00000000000000000000000000000001 A
1I
#44
0I
#45
b00000000000000000000000000000010 A
1I
#46
0I
#47
1.
1I
#48
0I
#49
12
b00000000000000000000000000000001 9
1I
#50
b0000 #
0(
0I
#51
02
06
b00000000000000000000000000000010 9
b00000000000000000000000000000000 A
0B
b000000001 E
1I
#52
0I
#53
12
b00000000000000000000000000000001 9
b00000000000000000000000000000001 A
1I
#54
0I
#55
02
b00000000000000000000000000000010 9
b00000000000000000000000000000010 A
b000000010 E
1I
#56
0I
#57
0.
12
b00000000000000000000000000000001 9
1I
#58
0I
#59
02
b00000000000000000000000000000010 9
b000000011 E
1I
#60
0I
#61
1I
#62
0I
#63
1I
#64
0I
#65
1I
#66
0I
#67
1I
#68
0I
#69
1I
#70
0I
#71
1I
#72
0I
#73
1I
#74
0I
#75
1I
#76
0I
#77
1I
#78
0I
#79
1I
#80
0I
#81
1I
#82
0I
#83
1I
#84
0I
#85
1I
#86
0I
#87
1I
#88
0I
#89
1I
#90
b1000 #
b0100 $
1(
0I
#91
b00000000000000000000000000000000 A
1B
1I
#92
0I
#93
b00000000000000000000000000000001 A
1I
#94
0I
#95
b00000000000000000000000000000010 A
1I
#96
0I
#97
1.
1I
#98
0I
#99
12
b00000000000000000000000000000001 9
1I
#100
b0000 #
0(
0I
#101
02
b00000000000000000000000000000010 9
b00000000000000000000000000000000 A
0B
b000000100 E
1I
#102
0I
#103
12
b00000000000000000000000000000001 9
b00000000000000000000000000000001 A
1I
#104
0I
#105
02
b00000000000000000000000000000010 9
b00000000000000000000000000000010 A
b000000101 E
1I
#106
0I
#107
0.
12
b00000000000000000000000000000001 9
1I
#108
0I
#109
02
b00000000000000000000000000000010 9
b000000110 E
1I
#110
0I
#111
1I
#112
0I
#113
1I
#114
0I
#115
1I
#116
0I
#117
1I
#118
0I
#119
1I
#120
0I
#121
1I
#122
0I
#123
1I
#124
0I
#125
1I
#126
0I
#127
1I
#128
0I
#129
1I
#130
0I
#131
1I
#132
0I
#133
1I
#134
0I
#135
1I
#136
0I
#137
1I
#138
0I
#139
1I
#140
b1000 #
b1000 $
1(
0I
#141
b00000000000000000000000000000000 A
1B
1I
#142
0I
#143
b00000000000000000000000000000001 A
1I
#144
0I
#145
b00000000000000000000000000000010 A
1I
#146
0I
#147
1.
1I
#148
0I
#149
12
b00000000000000000000000000000001 9
1I
#150
b0000 #
0(
0I
#151
02
b00000000000000000000000000000010 9
b00000000000000000000000000000000 A
0B
b000000111 E
1I
#152
0I
#153
12
b00000000000000000000000000000001 9
b00000000000000000000000000000001 A
1I
#154
0I
#155
02
b00000000000000000000000000000010 9
b00000000000000000000000000000010 A
b000001000 E
1I
#156
0I
#157
0.
12
b00000000000000000000000000000001 9
1I
#158
0I
#159
02
b00000000000000000000000000000010 9
b000001001 E
1I
#160
0I
#161
1I
#162
0I
#163
1I
#164
0I
#165
1I
#166
0I
#167
1I
#168
0I
#169
1I
#170
0I
#171
1I
#172
0I
#173
1I
#174
0I
#175
1I
#176
0I
#177
1I
#178
0I
#179
1I
#180
0I
#181
1I
#182
0I
#183
1I
#184
0I
#185
1I
#186
0I
#187
1I
#188
0I
#189
1I
#190
b1000 #
b1100 $
1(
0I
#191
b00000000000000000000000000000000 A
1B
1I
#192
0I
#193
b00000000000000000000000000000001 A
1I
#194
0I
#195
b00000000000000000000000000000010 A
1I
#196
0I
#197
1.
1I
#198
0I
#199
12
b00000000000000000000000000000001 9
1I
#200
b0000 #
0(
0I
#201
02
b00000000000000000000000000000010 9
b00000000000000000000000000000000 A
0B
b000001010 E
1I
#202
0I
#203
12
b00000000000000000000000000000001 9
b00000000000000000000000000000001 A
1I
#204
0I
#205
02
b00000000000000000000000000000010 9
b00000000000000000000000000000010 A
b000001011 E
1I
#206
0I
#207
0.
12
b00000000000000000000000000000001 9
1I
#208
0I
#209
02
b00000000000000000000000000000010 9
b000001100 E
1I
#210
0I
#211
1I
#212
0I
#213
1I
#214
0I
#215
1I
#216
0I
#217
1I
#218
0I
#219
1I
#220
0I
#221
1I
#222
0I
#223
1I
#224
0I
#225
1I
#226
0I
#227
1I
#228
0I
#229
1I
#230
0I
#231
1I
#232
0I
#233
1I
#234
0I
#235
1I
#236
0I
#237
1I
#238
0I
#239
1I
#240
b1000 #
b1010 $
1(
0I
#241
b00000000000000000000000000000000 A
1B
1I
#242
0I
#243
b00000000000000000000000000000001 A
1I
#244
0I
#245
b00000000000000000000000000000010 A
1I
#246
0I
#247
1.
1I
#248
0I
#249
12
b00000000000000000000000000000001 9
1I
#250
b0000 #
0(
0I
#251
02
b00000000000000000000000000000010 9
b00000000000000000000000000000000 A
0B
b000001101 E
1I
#252
0I
#253
12
b00000000000000000000000000000001 9
b00000000000000000000000000000001 A
1I
#254
0I
#255
02
b00000000000000000000000000000010 9
b00000000000000000000000000000010 A
b000001110 E
1I
#256
0I
#257
0.
12
b00000000000000000000000000000001 9
1I
#258
0I
#259
02
b00000000000000000000000000000010 9
b000001111 E
1I
#260
0I
#261
1I
#262
0I
#263
1I
#264
0I
#265
1I
#266
0I
#267
1I
#268
0I
#269
1I
#270
0I
#271
1I
#272
0I
#273
1I
#274
0I
#275
1I
#276
0I
#277
1I
#278
0I
#279
1I
#280
0I
#281
1I
#282
0I
#283
1I
#284
0I
#285
1I
#286
0I
#287
1I
#288
0I
#289
1I
#290
b0100 #
1'
0I
#291
b00000000000000000000000000000000 ?
1@
1I
#292
0I
#293
b00000000000000000000000000000001 ?
1I
#294
0I
#295
b00000000000000000000000000000010 ?
1I
#296
0I
#297
1/
1I
#298
0I
#299
b0001110 +
13
14
b00000000000000000000000000000011 9
1I
#300
b0000 #
0'
0I
#301
b0000000000000000000000000001 :
b00000000000000000000000000000000 ?
0@
b000000001 D
1I
#302
0I
#303
b0000000000000000000000000010 :
b00000000000000000000000000000001 ?
b000000010 D
1I
#304
0I
#305
b0000000000000000000000000011 :
b00000000000000000000000000000010 ?
b000000011 D
1I
#306
0I
#307
b000001000000001000 -
0/
b0100 5
b0000000000000000000000000100 :
b000000100 D
b01 F
b000001000 G
b000001000 H
1I
#308
0I
#309
b0000000000000000000000000101 :
b000000101 D
1I
#310
0I
#311
b0000000000000000000000000110 :
b000000110 D
1I
#312
0I
#313
b000001100000001100 -
b1000 5
b0000000000000000000000000111 :
b000000111 D
b10 F
b000001100 G
b000001100 H
1I
#314
0I
#315
b0000000000000000000000001000 :
b000001000 D
1I
#316
0I
#317
b0000000000000000000000001001 :
b000001001 D
1I
#318
0I
#319
b000001111000001111 -
b1100 5
b0000000000000000000000001010 :
b000001010 D
b11 F
b000001111 G
b000001111 H
1I
#320
0I
#321
b0000000000000000000000001011 :
b000001011 D
1I
#322
0I
#323
b0000000000000000000000001100 :
b000001100 D
1I
#324
0I
#325
b1000111 *
b1111111 +
b000001000000001100 -
b1010 5
b0000000000000000000000001101 :
b10 C
b000001101 D
b10 F
b000001000 G
b000001100 H
1I
#326
0I
#327
b0000000000000000000000001110 :
b000001110 D
1I
#328
0I
#329
16
b0000000000000000000000001111 :
b000001111 D
1I
#330
0I
#331
b0000000000000000000000010000 :
1I
#332
0I
#333
b0000000000000000000000010001 :
1I
#334
0I
#335
b0000000000000000000000010010 :
1I
#336
0I
#337
b0000000000000000000000010011 :
1I
#338
0I
#339
b0000000000000000000000010100 :
1I
#340
0I
#341
b0000000000000000000000010101 :
1I
#342
0I
#343
b0000000000000000000000010110 :
1I
#344
0I
#345
b0000000000000000000000010111 :
1I
#346
0I
#347
b0000000000000000000000011000 :
1I
#348
0I
#349
b0000000000000000000000011001 :
1I
#350
0I
#351
b0000000000000000000000011010 :
1I
#352
0I
#353
b0000000000000000000000011011 :
1I
#354
0I
#355
b0000000000000000000000011100 :
1I
#356
0I
#357
b0000000000000000000000011101 :
1I
#358
0I
#359
b0000000000000000000000011110 :
1I
#360
0I
#361
b0000000000000000000000011111 :
1I
#362
0I
#363
b0000000000000000000000100000 :
1I
#364
0I
#365
b0000000000000000000000100001 :
1I
#366
0I
#367
b0000000000000000000000100010 :
1I
#368
0I
#369
b0000000000000000000000100011 :
1I
#370
0I
#371
b0000000000000000000000100100 :
1I
#372
0I
#373
b0000000000000000000000100101 :
1I
#374
0I
#375
b0000000000000000000000100110 :
1I
#376
0I
#377
b0000000000000000000000100111 :
1I
#378
0I
#379
b0000000000000000000000101000 :
1I
#380
0I
#381
b0000000000000000000000101001 :
1I
#382
0I
#383
b0000000000000000000000101010 :
1I
#384
0I
#385
b0000000000000000000000101011 :
1I
#386
0I
#387
b0000000000000000000000101100 :
1I
#388
0I
#389
b0000000000000000000000101101 :
1I
#390
0I
#391
b0000000000000000000000101110 :
1I
#392
0I
#393
b0000000000000000000000101111 :
1I
#394
0I
#395
b0000000000000000000000110000 :
1I
#396
0I
#397
b0000000000000000000000110001 :
1I
#398
0I
#399
b0000000000000000000000110010 :
1I
#400
0I
#401
b0000000000000000000000110011 :
1I
#402
0I
#403
b0000000000000000000000110100 :
1I
#404
0I
#405
b0000000000000000000000110101 :
1I
#406
0I
#407
b0000000000000000000000110110 :
1I
#408
0I
#409
b0000000000000000000000110111 :
1I
#410
0I
#411
b0000000000000000000000111000 :
1I
#412
0I
#413
b0000000000000000000000111001 :
1I
#414
0I
#415
b0000000000000000000000111010 :
1I
#416
0I
#417
b0000000000000000000000111011 :
1I
#418
0I
#419
b0000000000000000000000111100 :
1I
#420
0I
#421
b0000000000000000000000111101 :
1I
#422
0I
#423
b0000000000000000000000111110 :
1I
#424
0I
#425
b0000000000000000000000111111 :
1I
#426
0I
#427
b0000000000000000000001000000 :
1I
#428
0I
#429
b0000000000000000000001000001 :
1I
#430
0I
#431
b0000000000000000000001000010 :
1I
#432
0I
#433
b0000000000000000000001000011 :
1I
#434
0I
#435
b0000000000000000000001000100 :
1I
#436
0I
#437
b0000000000000000000001000101 :
1I
#438
0I
#439
b0000000000000000000001000110 :
1I
#440
0I
#441
b0000000000000000000001000111 :
1I
#442
0I
#443
b0000000000000000000001001000 :
1I
#444
0I
#445
b0000000000000000000001001001 :
1I
#446
0I
#447
b0000000000000000000001001010 :
1I
#448
0I
#449
b0000000000000000000001001011 :
1I
#450
0I
#451
b0000000000000000000001001100 :
1I
#452
0I
#453
b0000000000000000000001001101 :
1I
#454
0I
#455
b0000000000000000000001001110 :
1I
#456
0I
#457
b0000000000000000000001001111 :
1I
#458
0I
#459
b0000000000000000000001010000 :
1I
#460
0I
#461
b0000000000000000000001010001 :
1I
#462
0I
#463
b0000000000000000000001010010 :
1I
#464
0I
#465
b0000000000000000000001010011 :
1I
#466
0I
#467
b0000000000000000000001010100 :
1I
#468
0I
#469
b0000000000000000000001010101 :
1I
#470
0I
#471
b0000000000000000000001010110 :
1I
#472
0I
#473
b0000000000000000000001010111 :
1I
#474
0I
#475
b0000000000000000000001011000 :
1I
#476
0I
#477
b0000000000000000000001011001 :
1I
#478
0I
#479
b0000000000000000000001011010 :
1I
#480
0I
#481
b0000000000000000000001011011 :
1I
#482
0I
#483
b0000000000000000000001011100 :
1I
#484
0I
#485
b0000000000000000000001011101 :
1I
#486
0I
#487
b0000000000000000000001011110 :
1I
#488
0I
#489
b0000000000000000000001011111 :
1I
#490
0I
#491
b0000000000000000000001100000 :
1I
#492
0I
#493
b0000000000000000000001100001 :
1I
#494
0I
#495
b0000000000000000000001100010 :
1I
#496
0I
#497
b0000000000000000000001100011 :
1I
#498
0I
#499
b0000000000000000000001100100 :
1I
#500
0I
#501
b0000000000000000000001100101 :
1I
#502
0I
#503
b0000000000000000000001100110 :
1I
#504
0I
#505
b0000000000000000000001100111 :
1I
#506
0I
#507
b0000000000000000000001101000 :
1I
#508
0I
#509
b0000000000000000000001101001 :
1I
#510
0I
#511
b0000000000000000000001101010 :
1I
#512
0I
#513
b0000000000000000000001101011 :
1I
#514
0I
#515
b0000000000000000000001101100 :
1I
#516
0I
#517
b0000000000000000000001101101 :
1I
#518
0I
#519
b0000000000000000000001101110 :
1I
#520
0I
#521
b0000000000000000000001101111 :
1I
#522
0I
#523
b0000000000000000000001110000 :
1I
#524
0I
#525
b0000000000000000000001110001 :
1I
#526
0I
#527
b0000000000000000000001110010 :
1I
#528
0I
#529
b0000000000000000000001110011 :
1I
#530
0I
#531
b0000000000000000000001110100 :
1I
#532
0I
#533
b0000000000000000000001110101 :
1I
#534
0I
#535
b0000000000000000000001110110 :
1I
#536
0I
#537
b0000000000000000000001110111 :
1I
#538
0I
#539
b0000000000000000000001111000 :
1I
#540
0I
#541
b0000000000000000000001111001 :
1I
#542
0I
#543
b0000000000000000000001111010 :
1I
#544
0I
#545
b0000000000000000000001111011 :
1I
#546
0I
#547
b0000000000000000000001111100 :
1I
#548
0I
#549
b0000000000000000000001111101 :
1I
#550
0I
#551
b0000000000000000000001111110 :
1I
#552
0I
#553
b0000000000000000000001111111 :
1I
#554
0I
#555
b0000000000000000000010000000 :
1I
#556
0I
#557
b0000000000000000000010000001 :
1I
#558
0I
#559
b0000000000000000000010000010 :
1I
#560
0I
#561
b0000000000000000000010000011 :
1I
#562
0I
#563
b0000000000000000000010000100 :
1I
#564
0I
#565
b0000000000000000000010000101 :
1I
#566
0I
#567
b0000000000000000000010000110 :
1I
#568
0I
#569
b0000000000000000000010000111 :
1I
#570
0I
#571
b0000000000000000000010001000 :
1I
#572
0I
#573
b0000000000000000000010001001 :
1I
#574
0I
#575
b0000000000000000000010001010 :
1I
#576
0I
#577
b0000000000000000000010001011 :
1I
#578
0I
#579
b0000000000000000000010001100 :
1I
#580
0I
#581
b0000000000000000000010001101 :
1I
#582
0I
#583
b0000000000000000000010001110 :
1I
#584
0I
#585
b0000000000000000000010001111 :
1I
#586
0I
#587
b0000000000000000000010010000 :
1I
#588
0I
#589
b0000000000000000000010010001 :
1I
#590
0I
#591
b0000000000000000000010010010 :
1I
#592
0I
#593
b0000000000000000000010010011 :
1I
#594
0I
#595
b0000000000000000000010010100 :
1I
#596
0I
#597
b0000000000000000000010010101 :
1I
#598
0I
#599
b0000000000000000000010010110 :
1I
#600
0I
#601
b0000000000000000000010010111 :
1I
#602
0I
#603
b0000000000000000000010011000 :
1I
#604
0I
#605
b0000000000000000000010011001 :
1I
#606
0I
#607
b0000000000000000000010011010 :
1I
#608
0I
