FIFO.sv
module fifo (
  input        clk,
  input        rst,
  input        we,
  input        re,
  input        del,
  input        [3:0] data_in,
  output reg   [3:0] data_out,
  output       empty,
  output       full
);
    //exact same thing as lab 2 FIFO
    //except 2 commented parts

    //changed the width to 256 (5-bit address)
    reg [3:0]       ram [255:0];

    localparam a_width = 8; // 1 wider than ram depth 
    reg [a_width:0] r_ptr, w_ptr;

    always @(posedge clk) begin
        if (rst) begin
            r_ptr <= 0;
            w_ptr <= 0; 
        end
        // added new rule to move back one pointer
        else if (del) w_ptr <= w_ptr -1;
        else begin
            if (we & ~full) begin
                ram[w_ptr[a_width-1:0]] <= data_in;
                w_ptr <= w_ptr + 1;
            end
            if (re & ~empty) begin
                data_out <= ram[r_ptr[a_width-1:0]];
                r_ptr <= r_ptr + 1;
            end
        end
    end

    assign empty = (r_ptr == w_ptr+1)? 1:0;
    assign full = r_ptr[a_width-1:0] != w_ptr[a_width-1:0]? 0: 
                    r_ptr[a_width] != w_ptr[a_width]? 1:0;

endmodule

fifo_tb.sv
module fifo_tb;
    // Step 1: Define test bench variables:
    logic clk; //Clk
    logic rst;
    logic we;
    logic re;
    logic del;
    logic [3:0] data_in;
    logic [3:0] data_out;
    logic empty;
    logic full;

    // Step 2: Instantiate Device Under Test:
    fifo DUT (.*); // SystemVerilog feature: `.*` automatically connects ports of the instantiated module to variables in this module with the same port/variable name!! So useful :D.

    // Step 3: Toggle the clock variable every 10 time units to create a clock signal **with period = 20 time units**:
    // initial forever #10 clk = ~clk; // forever is an infinite loop!

    // Log every clock cycle:
    initial begin
        forever begin // strobe: print values at end of the current timestep
            $strobe("t: %d ps, data_in = %b", $time, data_in);
            #(units); // every 0.25 units = 4Hz
        end
    end

    initial forever #10 clk = ~clk; // every 20ns = 50MHz (simulating board clock)

    localparam units = 20; // timescale for the simulation

    // Step 4: Initial block with initial inputs. To specify later inputs, use the delay operator `#`.
    initial begin
        $dumpfile("test_fifo.vcd");  // Tell the simulator to dump variables into the 'waveform.vcd' file during the simulation. Required to produce a waveform .vcd file.
        $dumpvars();
        clk = 0;
        #(4*units);

        // Nothing should be written to BRAM
        re = 0;
        we = 0;
        del = 0;
        rst = 0;
        #(1*units);
        data_in = 4'b0111;
        #(1*units);
        data_in = 4'b0100;
        #(1*units);
        data_in = 4'b0011;
        #(1*units);

        
        #(1*units);
        data_in = 4'b0111;
        we = 1; // Write Enable
        #(1*units);
        data_in = 4'b0100;
        #(1*units);
        data_in = 4'b0010;
        #(1*units);
        del = 1; // Delete
        #(1*units);
        del = 0; // Delete off
        data_in = 4'b0010;
        #(1*units);
        rst = 1; // Reset
        #(4*units);
        // 3 instructions should have been added, then 1 removed, then 1 added, then rst

        rst = 0; // Reset off
        data_in = 4'b0000;
        #(1*units);
        data_in = 4'b0001;
        #(1*units);
        data_in = 4'b0010;
        #(1*units);
        data_in = 4'b0011;
        #(1*units);
        data_in = 4'b0100;
        #(1*units);
        data_in = 4'b0101;
        #(1*units);
        data_in = 4'b0110;
        #(1*units);
        we = 0; // Write disable
        re = 1; // Read enable
        // Should output to data_out until empty
        #(20*units)


        $finish(); // Important: must end simulation (or it will go on forever!)
    end

endmodule

waveforms/test_fifo (5).vcd
$version Generated by VerilatedVcd $end
$timescale 1ps $end

 $scope module TOP $end
  $scope module fifo_tb $end
   $var wire  1 - clk $end
   $var wire  4 ' data_in [3:0] $end
   $var wire  4 ( data_out [3:0] $end
   $var wire  1 & del $end
   $var wire  1 ) empty $end
   $var wire  1 * full $end
   $var wire  1 % re $end
   $var wire  1 # rst $end
   $var wire 32 . units [31:0] $end
   $var wire  1 $ we $end
   $scope module DUT $end
    $var wire 32 / a_width [31:0] $end
    $var wire  1 - clk $end
    $var wire  4 ' data_in [3:0] $end
    $var wire  4 ( data_out [3:0] $end
    $var wire  1 & del $end
    $var wire  1 ) empty $end
    $var wire  1 * full $end
    $var wire  9 + r_ptr [8:0] $end
    $var wire  1 % re $end
    $var wire  1 # rst $end
    $var wire  9 , w_ptr [8:0] $end
    $var wire  1 $ we $end
   $upscope $end
  $upscope $end
 $upscope $end
$enddefinitions $end


#0
0#
0$
0%
0&
b0000 '
b0000 (
1)
0*
b000000000 +
b000000000 ,
0-
b00000000000000000000000000010100 .
b00000000000000000000000000001000 /
#10
1-
#20
0-
#30
1-
#40
0-
#50
1-
#60
0-
#70
1-
#80
0-
#90
1-
#100
b0111 '
0-
#110
1-
#120
b0100 '
0-
#130
1-
#140
b0011 '
0-
#150
1-
#160
0-
#170
1-
#180
1$
b0111 '
0-
#190
0)
b000000001 ,
1-
#200
b0100 '
0-
#210
b000000010 ,
1-
#220
b0010 '
0-
#230
b000000011 ,
1-
#240
1&
0-
#250
b000000010 ,
1-
#260
0&
0-
#270
b000000011 ,
1-
#280
1#
0-
#290
1)
b000000000 ,
1-
#300
0-
#310
1-
#320
0-
#330
1-
#340
0-
#350
1-
#360
0#
b0000 '
0-
#370
0)
b000000001 ,
1-
#380
b0001 '
0-
#390
b000000010 ,
1-
#400
b0010 '
0-
#410
b000000011 ,
1-
#420
b0011 '
0-
#430
b000000100 ,
1-
#440
b0100 '
0-
#450
b000000101 ,
1-
#460
b0101 '
0-
#470
b000000110 ,
1-
#480
b0110 '
0-
#490
b000000111 ,
1-
#500
0$
1%
0-
#510
b000000001 +
1-
#520
0-
#530
b0001 (
b000000010 +
1-
#540
0-
#550
b0010 (
b000000011 +
1-
#560
0-
#570
b0011 (
b000000100 +
1-
#580
0-
#590
b0100 (
b000000101 +
1-
#600
0-
#610
b0101 (
b000000110 +
1-
#620
0-
#630
b0110 (
1)
b000000111 +
1-
