torque_display.sv
module torque_display(
    input enable,
    input      [1:0]  instruction,
    input      [1:0]  torque,
    output logic [8:0]  left_LED, // LEDR[17:9]
    output logic [8:0]  right_LED // LEDR[8:0]
);

    //torque values
    logic [3:0] zero = 4'b0000;
    logic [3:0] quart = 4'b0010; 
    logic [3:0] half = 4'b1000; 
    logic [3:0] three_quart = 4'b1100;
    logic [3:0] full = 4'b1111;

    always_comb begin: torque_display
        if (~enable) begin
            left_LED = {zero, 1'b0, zero};
            right_LED = {zero, 1'b0, zero};
        end

        //no extension version
        /* else begin
            left_LED = (instruction == 2'b00)? {zero, 1'b0, full}:  
                        (instruction == 2'b01)? {full, 1'b0, zero}: 
                        (instruction == 2'b10)? {zero, 1'b0, three_quart}:
                        (instruction == 2'b11)? {zero, 1'b0, full} : {zero, 1'b0, zero};

            right_LED = (instruction == 2'b00)? {zero, 1'b0, full}:
                        (instruction == 2'b01)? {full, 1'b0, zero}:
                        (instruction == 2'b10)? {zero, 1'b0, full}:
                        (instruction == 2'b11)? {zero, 1'b0, three_quart} : {zero, 1'b0, zero};
        end */   
		  
		  //extension version
        else begin
				case (instruction)
              2'b00:begin //forward
                 left_LED = (torque == 2'b00)? {zero, 1'b0, zero}:  
                     (torque == 2'b01)? {zero, 1'b0, half}: 
                     (torque == 2'b10)? {zero, 1'b0, three_quart}:
                     (torque == 2'b11)? {zero, 1'b0, full} : {zero, 1'b0, zero};

                 right_LED = (torque == 2'b00)? {zero, 1'b0, zero}:  
                     (torque == 2'b01)? {zero, 1'b0, half}: 
                     (torque == 2'b10)? {zero, 1'b0, three_quart}:
                     (torque == 2'b11)? {zero, 1'b0, full} : {zero, 1'b0, zero};
             end
             2'b01:begin //reverse
                 left_LED = (torque == 2'b00)? {zero, 1'b0, zero}:  
                     (torque == 2'b01)? {half, 1'b0, zero}: 
                     (torque == 2'b10)? {three_quart, 1'b0, zero}:
                     (torque == 2'b11)? {full, 1'b0, zero} : {zero, 1'b0, zero};

                 right_LED = (torque == 2'b00)? {zero, 1'b0, zero}:  
                     (torque == 2'b01)? {half, 1'b0, zero}: 
                     (torque == 2'b10)? {three_quart, 1'b0, zero}:
                     (torque == 2'b11)? {full, 1'b0, zero} : {zero, 1'b0, zero};
             end
             2'b10:begin //left
                 left_LED = (torque == 2'b00)? {zero, 1'b0, zero}:  
                     (torque == 2'b01)? {zero, 1'b0, quart}: 
                     (torque == 2'b10)? {zero, 1'b0, half}:
                     (torque == 2'b11)? {zero, 1'b0, full} : {zero, 1'b0, zero};

                 right_LED = (torque == 2'b00)? {zero, 1'b0, zero}:  
                     (torque == 2'b01)? {zero, 1'b0, half}: 
                     (torque == 2'b10)? {zero, 1'b0, three_quart}:
                     (torque == 2'b11)? {zero, 1'b0, full} : {zero, 1'b0, zero};
             end
             2'b11:begin
                 left_LED = (torque == 2'b00)? {zero, 1'b0, zero}:  
                     (torque == 2'b01)? {zero, 1'b0, half}: 
                     (torque == 2'b10)? {zero, 1'b0, three_quart}:
                     (torque == 2'b11)? {zero, 1'b0, full} : {zero, 1'b0, zero};

                 right_LED = (torque == 2'b00)? {zero, 1'b0, zero}:  
                     (torque == 2'b01)? {zero, 1'b0, quart}: 
                     (torque == 2'b10)? {zero, 1'b0, half}:
                     (torque == 2'b11)? {zero, 1'b0, full} : {zero, 1'b0, zero};
             end
          endcase  
         end 

    end
endmodule

torque_display_tb.sv
module torque_display_tb;
    // Step 1: Define test bench variables:
    logic enable;
    logic [1:0]  instruction;
    logic [1:0]  torque; 
    logic [8:0]  left_LED; // LEDR[17:9]
    logic [8:0]  right_LED; // LEDR[8:0]

    // Step 2: Instantiate Device Under Test:
    torque_display DUT (.*); // SystemVerilog feature: `.*` automatically connects ports of the instantiated module to variables in this module with the same port/variable name!! So useful :D.

    // Step 3: Toggle the clock variable every 10 time units to create a clock signal **with period = 20 time units**:
    // initial forever #10 clk = ~clk; // forever is an infinite loop!

    // Log every clock cycle:
    initial begin
        forever begin // strobe: print values at end of the current timestep
            $strobe("t: %d ps, enable: %b, direc: %b, torque: %b", $time, enable,instruction, torque);
            $strobe("left_LED: %b", left_LED);
            $strobe("right_LED: %b", right_LED);
            #1;
        end
    end

    // Step 4: Initial block with initial inputs. To specify later inputs, use the delay operator `#`.
    initial begin
        $dumpfile("torque_display.vcd");  // Tell the simulator to dump variables into the 'waveform.vcd' file during the simulation. Required to produce a waveform .vcd file.
        $dumpvars();
        enable = 1;
        instruction = 0;
        torque = 0;

        repeat(15)begin
            #1
            instruction = (torque == 2'b11)? instruction + 1: instruction; 
            torque = torque + 1'b1;
        end       
            
        #1 enable = 0;
        #1
        $finish(); // Important: must end simulation (or it will go on forever!)
    end

endmodule

waveforms/torque_display.vcd
$version Generated by VerilatedVcd $end
$timescale 1ps $end

 $scope module TOP $end
  $scope module torque_display_tb $end
   $var wire  1 # enable $end
   $var wire  2 $ instruction [1:0] $end
   $var wire  9 & left_LED [8:0] $end
   $var wire  9 ' right_LED [8:0] $end
   $var wire  2 % torque [1:0] $end
   $scope module DUT $end
    $var wire  1 # enable $end
    $var wire  4 , full [3:0] $end
    $var wire  4 * half [3:0] $end
    $var wire  2 $ instruction [1:0] $end
    $var wire  9 & left_LED [8:0] $end
    $var wire  4 ) quart [3:0] $end
    $var wire  9 ' right_LED [8:0] $end
    $var wire  4 + three_quart [3:0] $end
    $var wire  2 % torque [1:0] $end
    $var wire  4 ( zero [3:0] $end
   $upscope $end
  $upscope $end
 $upscope $end
$enddefinitions $end


#0
1#
b00 $
b00 %
b000000000 &
b000000000 '
b0000 (
b0010 )
b1000 *
b1100 +
b1111 ,
#1
b01 %
b000001000 &
b000001000 '
#2
b10 %
b000001100 &
b000001100 '
#3
b11 %
b000001111 &
b000001111 '
#4
b01 $
b00 %
b000000000 &
b000000000 '
#5
b01 %
b100000000 &
b100000000 '
#6
b10 %
b110000000 &
b110000000 '
#7
b11 %
b111100000 &
b111100000 '
#8
b10 $
b00 %
b000000000 &
b000000000 '
#9
b01 %
b000000010 &
b000001000 '
#10
b10 %
b000001000 &
b000001100 '
#11
b11 %
b000001111 &
b000001111 '
#12
b11 $
b00 %
b000000000 &
b000000000 '
#13
b01 %
b000001000 &
b000000010 '
#14
b10 %
b000001100 &
b000001000 '
#15
b11 %
b000001111 &
b000001111 '
#16
0#
b000000000 &
b000000000 '
